gaussianmaster/__init__.py
gaussianmaster/main.py
gaussianmaster-0.1.dist-info/WHEEL
gaussianmaster-0.1.dist-info/METADATA
gaussianmaster-0.1.dist-info/RECORD
