Metadata-Version: 2.1
Name: gaussianmaster
Version: 0.1
Summary: GaussianMaster is ready to go!
Author-email: Michał Pocheć <lysy.pochec@gmail.com>
Requires-Python: >=3.5
Requires-Dist: numpy >=1.23.1
Requires-Dist: pandas >=1.4.3
Project-URL: Home, https://github.com/panpochec/GaussianMaster
